Metadata-Version: 1.0
Name: pip-packageexample
Version: 0.0.2
Summary:  paquete de prueba
Home-page: https://github.com/elijeldres/pip_packageExample 
Author:  Elijeldres
Author-email: UNKNOWN
License: MIT
Platform: UNKNOWN
